<SliderGroups>
  <Group name="1CBBE DemCollection">
    <Member name="1CBBE DemC Bikini Bot 1"/>
    <Member name="1CBBE DemC Bikini Bot 2"/>
    <Member name="1CBBE DemC Bikini Bot 3"/>
    <Member name="1CBBE DemC Bikini Bot 4"/>
    <Member name="1CBBE DemC Bikini Top 1"/>
    <Member name="1CBBE DemC Bikini Top 2"/>
    <Member name="1CBBE DemC Bikini Top 3"/>
    <Member name="1CBBE DemC Bikini Top 4"/>
    <Member name="1CBBE DemC EvaBikini Bot 1"/>
    <Member name="1CBBE DemC EvaBikini Bot 2"/>
    <Member name="1CBBE DemC EvaBikini Bot 5"/>
    <Member name="1CBBE DemC EvaBikini Bot 6"/>
    <Member name="1CBBE DemC EvaBikini Bot 7"/>
    <Member name="1CBBE DemC EvaBikini Bot 8"/>
    <Member name="1CBBE DemC EvaBikini Top 1"/>
    <Member name="1CBBE DemC EvaBikini Top 2"/>
    <Member name="1CBBE DemC EvaBikini Top 5"/>
    <Member name="1CBBE DemC EvaBikini Top 6"/>
    <Member name="1CBBE DemC EvaBikini Top 7"/>
    <Member name="1CBBE DemC EvaBikini Top 8"/>
    <Member name="1CBBE DemC EvaLif"/>
    <Member name="1CBBE DemC EvaString"/>
    <Member name="1CBBE DemC LB Boots 1"/>
    <Member name="1CBBE DemC LB Boots 2"/>
    <Member name="1CBBE DemC LBStock01"/>
    <Member name="1CBBE DemC LBStock02"/>
    <Member name="1CBBE DemC LBStock03"/>
    <Member name="1CBBE DemC LBStock04"/>
    <Member name="1CBBE DemC LBStock05"/>
    <Member name="1CBBE DemC Panty 1"/>
    <Member name="1CBBE DemC Panty 10"/>
    <Member name="1CBBE DemC Panty 11"/>
    <Member name="1CBBE DemC Panty 2"/>
    <Member name="1CBBE DemC Panty 3"/>
    <Member name="1CBBE DemC Panty 4"/>
    <Member name="1CBBE DemC Panty 5"/>
    <Member name="1CBBE DemC Panty 6"/>
    <Member name="1CBBE DemC Panty 7"/>
    <Member name="1CBBE DemC Panty 8"/>
    <Member name="1CBBE DemC Panty 9"/>
    <Member name="1CBBE DemC PantyHose B01"/>
    <Member name="1CBBE DemC PantyHose B02"/>
    <Member name="1CBBE DemC PantyHose B03"/>
    <Member name="1CBBE DemC PantyHose B04"/>
    <Member name="1CBBE DemC PantyHose B05"/>
    <Member name="1CBBE DemC RitualBoots"/>
    <Member name="1CBBE DemC RitualStockings"/>
    <Member name="1CBBE DemC Top01"/>
    <Member name="1CBBE DemC Top02"/>
    <Member name="1CBBE DemC Top03"/>
    <Member name="1CBBE DemC Top04"/>
    <Member name="1CBBE DemC Top05"/>
  </Group>
  <Group name="1CBBE ForestNymph">
    <Member name="1CBBE ForestNymph Bot"/>
    <Member name="1CBBE ForestNymph Top"/>
  </Group>
  <Group name="1CBBE Goma BikiniSet">
    <Member name="1CBBE Goma AnkletsA"/>
    <Member name="1CBBE Goma AnkletsB"/>
    <Member name="1CBBE Goma Armlets"/>
    <Member name="1CBBE Goma Bracelets"/>
    <Member name="1CBBE Goma C-String"/>
    <Member name="1CBBE Goma C-String2"/>
    <Member name="1CBBE Goma Caviar"/>
    <Member name="1CBBE Goma Caviar Bot"/>
    <Member name="1CBBE Goma CaviarNet"/>
    <Member name="1CBBE Goma Gold Sandals"/>
    <Member name="1CBBE Goma GoldArmlets"/>
    <Member name="1CBBE Goma GoldNeck"/>
    <Member name="1CBBE Goma GoldPierce"/>
    <Member name="1CBBE Goma GoldPierce Belly"/>
    <Member name="1CBBE Goma GoldPierce Body"/>
    <Member name="1CBBE Goma GoldThighs"/>
    <Member name="1CBBE Goma GoldThighs L"/>
    <Member name="1CBBE Goma GoldThighs R"/>
    <Member name="1CBBE Goma Heels"/>
    <Member name="1CBBE Goma Heels2"/>
    <Member name="1CBBE Goma Hutomomo"/>
    <Member name="1CBBE Goma MB1"/>
    <Member name="1CBBE Goma MB1 Bot"/>
    <Member name="1CBBE Goma MB10"/>
    <Member name="1CBBE Goma MB10 Bot"/>
    <Member name="1CBBE Goma MB10B"/>
    <Member name="1CBBE Goma MB10B Bot"/>
    <Member name="1CBBE Goma MB11"/>
    <Member name="1CBBE Goma MB11Pants"/>
    <Member name="1CBBE Goma MB2"/>
    <Member name="1CBBE Goma MB4"/>
    <Member name="1CBBE Goma MB4 Bot"/>
    <Member name="1CBBE Goma MB5"/>
    <Member name="1CBBE Goma MB7"/>
    <Member name="1CBBE Goma MB7 Bot"/>
    <Member name="1CBBE Goma MB7B Bot"/>
    <Member name="1CBBE Goma MB7C Bot"/>
    <Member name="1CBBE Goma MB7D"/>
    <Member name="1CBBE Goma MB7D Bot"/>
    <Member name="1CBBE Goma MB7b"/>
    <Member name="1CBBE Goma MB7c"/>
    <Member name="1CBBE Goma MB9"/>
    <Member name="1CBBE Goma MB9 Bot"/>
    <Member name="1CBBE Goma MB9b"/>
    <Member name="1CBBE Goma MB9b Bot"/>
    <Member name="1CBBE Goma Nippless01"/>
    <Member name="1CBBE Goma Nippless02"/>
    <Member name="1CBBE Goma PierceA"/>
    <Member name="1CBBE Goma PierceB"/>
    <Member name="1CBBE Goma Rings"/>
    <Member name="1CBBE Goma TattooChokerAnkle"/>
    <Member name="1CBBE Goma TattooChokerWrist"/>
    <Member name="1CBBE Goma Tshirt01"/>
    <Member name="1CBBE Goma Tshirt02"/>
  </Group>
  <Group name="1CBBE GomaEgypt">
    <Member name="1CBBE GomaEgypt Amulet"/>
    <Member name="1CBBE GomaEgypt Body"/>
    <Member name="1CBBE GomaEgypt Hands"/>
    <Member name="1CBBE GomaEgypt Heels"/>
    <Member name="1CBBE GomaEgypt Jewelry"/>
    <Member name="1CBBE GomaEgypt Legs"/>
    <Member name="1CBBE GomaEgypt Nip"/>
    <Member name="1CBBE GomaEgypt Pants"/>
  </Group>
  <Group name="1CBBE Tifa">
    <Member name="1CBBE Tifa Gloves"/>
    <Member name="1CBBE Tifa Panty"/>
    <Member name="1CBBE Tifa Skirt"/>
    <Member name="1CBBE Tifa Sneakers"/>
    <Member name="1CBBE Tifa Suspenders"/>
    <Member name="1CBBE Tifa Top"/>
  </Group>
  <Group name="1CBBE kuwa Pantyhose">
    <Member name="1CBBE Kuwa Pantyhose"/>
  </Group>
  <Group name="1CBBEDOAStringBikini">
    <Member name="1CBBE DOAStringBikini"/>
  </Group>
  <Group name="1CbbeEHBunny">
    <Member name="1CBBE Bunny Black"/>
    <Member name="1CBBE Bunny Black Trans"/>
    <Member name="1CBBE Bunny Blue"/>
    <Member name="1CBBE Bunny Blue Trans"/>
    <Member name="1CBBE Bunny Pink"/>
    <Member name="1CBBE Bunny Pink Trans"/>
    <Member name="1CBBE Bunny Red"/>
    <Member name="1CBBE Bunny Red Trans"/>
  </Group>
  <Group name="Angel High Heels Boots">
    <Member name="Angel High Heels Boots"/>
  </Group>
  <Group name="Angel Stiletto Boots">
    <Member name="Angel Stiletto Boots"/>
  </Group>
  <Group name="Angel Vixen Armor Complete [HDT]">
    <Member name="Angel Vixen Armor Complete [HDT]"/>
  </Group>
  <Group name="Angel Vixen Armor Lite [HDT]">
    <Member name="Angel Vixen Armor Lite [HDT]"/>
  </Group>
  <Group name="Angel Vixen Armor No Skirt [HDT]">
    <Member name="Angel Vixen Armor No Skirt [HDT]"/>
  </Group>
  <Group name="Angel Vixen Boots">
    <Member name="Angel Vixen Boots"/>
  </Group>
  <Group name="Angel Vixen Bracers">
    <Member name="Angel Vixen Bracers"/>
  </Group>
  <Group name="Angel Vixen Gloves">
    <Member name="Angel Vixen Gloves"/>
  </Group>
  <Group name="Angel Vixen Long Gloves">
    <Member name="Angel Vixen Long Gloves"/>
  </Group>
  <Group name="Apron">
    <Member name="Apron"/>
  </Group>
  <Group name="Apron Damaged">
    <Member name="Apron Damaged"/>
  </Group>
  <Group name="Aradia Naughty Lingerie 1">
    <Member name="Aradia Naughty Lingerie 1"/>
  </Group>
  <Group name="Aradia Naughty Lingerie 2">
    <Member name="Aradia Naughty Lingerie 2"/>
  </Group>
  <Group name="Aradia Naughty Lingerie 2b">
    <Member name="Aradia Naughty Lingerie 2b"/>
  </Group>
  <Group name="LUSH SetA MagicMoon Boots">
    <Member name="LUSH SetA MagicMoon Boots"/>
  </Group>
  <Group name="LUSH SetA MagicMoon Gauntlets">
    <Member name="LUSH SetA MagicMoon Bracers"/>
  </Group>
  <Group name="LUSH SetA MagicMoon Panty Black">
    <Member name="LUSH SetA MagicMoon Panty Black"/>
  </Group>
  <Group name="LUSH SetA MagicMoon Panty Lavender">
    <Member name="LUSH SetA MagicMoon Panty Lavender"/>
  </Group>
  <Group name="LUSH SetA MagicMoon Panty Orange">
    <Member name="LUSH SetA MagicMoon Panty Orange"/>
  </Group>
  <Group name="LUSH SetA MagicMoon Panty Red">
    <Member name="LUSH SetA MagicMoon Panty Red"/>
  </Group>
</SliderGroups>
